Metadata-Version: 2.1
Name: pythonmachineid
Version: 0.0.1.dev1
Summary: Python Machine Id library
Home-page: http://pypi.python.org/pypi/pythonmachineid_v001.dev1/
Author: Ernest Offiong
Author-email: ernest.offiong@gmail.com
License: MIT
Platform: UNKNOWN
Classifier: Intended Audience :: Developers
Classifier: Topic :: Software Development :: Build Tools
Classifier: License :: OSI Approved :: MIT License
Classifier: Programming Language :: Python :: 3
Classifier: Programming Language :: Python :: 3.4
Classifier: Programming Language :: Python :: 3.5
Classifier: Programming Language :: Python :: 3.6
Requires-Python: >=3
License-File: LICENSE.txt
